fanalysis/__init__.py
fanalysis/base.py
fanalysis/ca.py
fanalysis/mca.py
fanalysis/pca.py
fanalysis/tests/__init__.py
fanalysis/tests/ca_col_contrib.txt
fanalysis/tests/ca_col_coord.txt
fanalysis/tests/ca_col_cos2.txt
fanalysis/tests/ca_col_labels.txt
fanalysis/tests/ca_data.txt
fanalysis/tests/ca_df_col_header.txt
fanalysis/tests/ca_df_row_header.txt
fanalysis/tests/ca_eig.txt
fanalysis/tests/ca_row_contrib.txt
fanalysis/tests/ca_row_coord.txt
fanalysis/tests/ca_row_cos2.txt
fanalysis/tests/ca_row_labels.txt
fanalysis/tests/mca_col_contrib.txt
fanalysis/tests/mca_col_coord.txt
fanalysis/tests/mca_col_cos2.txt
fanalysis/tests/mca_col_labels.txt
fanalysis/tests/mca_col_labels_numeric.txt
fanalysis/tests/mca_col_labels_string.txt
fanalysis/tests/mca_data_numeric.txt
fanalysis/tests/mca_data_string.txt
fanalysis/tests/mca_eig.txt
fanalysis/tests/mca_row_contrib.txt
fanalysis/tests/mca_row_coord.txt
fanalysis/tests/mca_row_cos2.txt
fanalysis/tests/mca_row_labels.txt
fanalysis/tests/pca_col_contrib_scale_unit_false.txt
fanalysis/tests/pca_col_contrib_scale_unit_true.txt
fanalysis/tests/pca_col_coord_scale_unit_false.txt
fanalysis/tests/pca_col_coord_scale_unit_true.txt
fanalysis/tests/pca_col_cor_scale_unit_false.txt
fanalysis/tests/pca_col_cor_scale_unit_true.txt
fanalysis/tests/pca_col_cos2_scale_unit_false.txt
fanalysis/tests/pca_col_cos2_scale_unit_true.txt
fanalysis/tests/pca_col_labels.txt
fanalysis/tests/pca_data.txt
fanalysis/tests/pca_eig_scale_unit_false.txt
fanalysis/tests/pca_eig_scale_unit_true.txt
fanalysis/tests/pca_row_contrib_scale_unit_false.txt
fanalysis/tests/pca_row_contrib_scale_unit_true.txt
fanalysis/tests/pca_row_coord_scale_unit_false.txt
fanalysis/tests/pca_row_coord_scale_unit_true.txt
fanalysis/tests/pca_row_cos2_scale_unit_false.txt
fanalysis/tests/pca_row_cos2_scale_unit_true.txt
fanalysis/tests/pca_row_labels.txt
fanalysis/tests/test_base.py
fanalysis/tests/test_ca.py
fanalysis-0.0.1.dist-info/METADATA
fanalysis-0.0.1.dist-info/RECORD
fanalysis-0.0.1.dist-info/WHEEL
fanalysis-0.0.1.dist-info/top_level.txt
