Metadata-Version: 2.1
Name: fanalysis
Version: 0.0.1
Summary: Python module for Factorial Analysis
Home-page: UNKNOWN
Author: OlivierGarciaDev
Author-email: o.garcia.dev@gmail.com
License: UNKNOWN
Platform: UNKNOWN
Classifier: Programming Language :: Python :: 3
Classifier: License :: OSI Approved :: MIT License
Classifier: Operating System :: OS Independent
Requires-Python: >=3
Requires-Dist: numpy (>=1.11.0)
Requires-Dist: matplotlib (>=2.0.0)
Requires-Dist: scikit-learn (>=0.18.0)
Requires-Dist: pandas (>=0.19.0)
